crosslab/soa_client/__init__.py
crosslab/soa_client/connection.py
crosslab/soa_client/connection_webrtc.py
crosslab/soa_client/device_handler.py
crosslab/soa_client/message_handling.py
crosslab/soa_client/py.typed
crosslab/soa_client/schemas.py
crosslab/soa_client/service.py
crosslab/soa_client/media/__init__.py
crosslab/soa_client/media/gst_track.py
crosslab/soa_client/media/udp_track.py
crosslab_soa_client-0.0.1.dist-info/METADATA
crosslab_soa_client-0.0.1.dist-info/WHEEL
crosslab_soa_client-0.0.1.dist-info/top_level.txt
crosslab_soa_client-0.0.1.dist-info/RECORD
