Metadata-Version: 2.1
Name: crosslab-soa-client
Version: 0.0.1
Summary: The CrossLab SOA Client
Author: Johannes Nau
Author-email: johannes.nau@tu-ilmenau.de
Classifier: Programming Language :: Python :: 3
Classifier: License :: Other/Proprietary License
Classifier: Operating System :: OS Independent
Requires-Python: <3.11,>=3.8
Requires-Dist: crosslab-aiortc
Requires-Dist: crosslab-api-client
